vivarium_bioscrape
