Metadata-Version: 2.1
Name: vivarium-bioscrape
Version: 0.0.0.6
Summary: UNKNOWN
Home-page: https://github.com/vivarium-collective/vivarium-bioscrape
Author: William Poole, Eran Agmon, Ryan Spangler
Author-email: 
License: MIT
Platform: UNKNOWN
